pythonpoet/__init__.py
pythonpoet/pythonpoet.py
pythonpoet/types/__init__.py
pythonpoet/types/class_.py
pythonpoet/types/decorator.py
pythonpoet/types/field.py
pythonpoet/types/import_.py
pythonpoet/types/method.py
PythonPoet-0.1.3.dist-info/LICENSE
PythonPoet-0.1.3.dist-info/METADATA
PythonPoet-0.1.3.dist-info/WHEEL
PythonPoet-0.1.3.dist-info/top_level.txt
PythonPoet-0.1.3.dist-info/RECORD
