Metadata-Version: 2.1
Name: PythonPoet
Version: 0.1.3
Summary: API for generating Python source code from runtime.
Home-page: https://github.com/Pelfox/PythonPoet
Author: Pelfox
Author-email: me@pelfox.dev
Project-URL: Bug Tracker, https://github.com/Pelfox/PythonPoet/issues
Classifier: Programming Language :: Python :: 3
Classifier: License :: OSI Approved :: MIT License
Classifier: Operating System :: OS Independent
Requires-Python: >=3.10
License-File: LICENSE
